{
  "H-01": {
    "code": "H-01",
    "name": "Trolley Storage",
    "risk": "high",
    "interactive": true,
    "left": 37.86,
    "top": 28.9379,
    "width": 2.65,
    "height": 9.5346,
    "svgPath": null,
    "fillColor": "#22C55E",
    "fillOpacity": 0.18,
    "strokeColor": "#22C55E",
    "strokeWidth": 1.0,
    "assetCount": 21
  },
  "H-02": {
    "code": "H-02",
    "name": "HR Area",
    "risk": "high",
    "interactive": true,
    "left": 37.8341,
    "top": 39.701,
    "width": 2.8287,
    "height": 56.7158,
    "svgPath": "M 38.2651 39.701 L 40.6627 39.701 L 40.528 96.3145 L 37.861 96.4169 L 37.8341 86.5889 L 38.2651 86.5889 L 38.1843 69.0827 L 37.8879 69.0827 L 37.8879 65.1924 L 38.1843 65.0901 L 38.2651 39.701 Z",
    "fillColor": "#22C55E",
    "fillOpacity": 0.18,
    "strokeColor": "#22C55E",
    "strokeWidth": 1.0,
    "assetCount": 99
  },
  "H-03": {
    "code": "H-03",
    "name": "Trolley Tray Wash Up Room",
    "risk": "high",
    "interactive": true,
    "left": 28.9519,
    "top": 28.4669,
    "width": 8.7015,
    "height": 10.4423,
    "svgPath": "M 28.9519 28.5693 L 37.6534 28.4669 L 37.6265 38.9092 L 30.6491 38.8068 L 30.6491 35.6332 L 28.9789 35.326 L 28.9519 28.5693 Z",
    "fillColor": "#22C55E",
    "fillOpacity": 0.18,
    "strokeColor": "#22C55E",
    "strokeWidth": 1.0,
    "assetCount": 47
  },
  "H-04": {
    "code": "H-04",
    "name": "Blast Chiller 1",
    "risk": "high",
    "interactive": true,
    "left": 35.5252,
    "top": 40.2077,
    "width": 2.4824,
    "height": 7.1473,
    "svgPath": null,
    "fillColor": "#22C55E",
    "fillOpacity": 0.18,
    "strokeColor": "#22C55E",
    "strokeWidth": 1.0,
    "assetCount": 26
  },
  "H-05": {
    "code": "H-05",
    "name": "Blast Chiller 2",
    "risk": "high",
    "interactive": true,
    "left": 35.5253,
    "top": 49.0903,
    "width": 2.4824,
    "height": 7.1473,
    "svgPath": null,
    "fillColor": "#22C55E",
    "fillOpacity": 0.18,
    "strokeColor": "#22C55E",
    "strokeWidth": 1.0,
    "assetCount": 24
  },
  "H-06": {
    "code": "H-06",
    "name": "Blast Chiller 3",
    "risk": "high",
    "interactive": true,
    "left": 35.5253,
    "top": 57.4601,
    "width": 2.3348,
    "height": 7.1473,
    "svgPath": null,
    "fillColor": "#22C55E",
    "fillOpacity": 0.18,
    "strokeColor": "#22C55E",
    "strokeWidth": 1.0,
    "assetCount": 20
  },
  "H-07": {
    "code": "H-07",
    "name": "Holding Chiller 1",
    "risk": "high",
    "interactive": true,
    "left": 32.4901,
    "top": 40.2162,
    "width": 2.65,
    "height": 24.3766,
    "svgPath": null,
    "fillColor": "#22C55E",
    "fillOpacity": 0.18,
    "strokeColor": "#22C55E",
    "strokeWidth": 1.0,
    "assetCount": 48
  },
  "H-08": {
    "code": "H-08",
    "name": "Blast Chiller 4",
    "risk": "high",
    "interactive": true,
    "left": 35.5921,
    "top": 70.3258,
    "width": 2.3348,
    "height": 7.1473,
    "svgPath": null,
    "fillColor": "#22C55E",
    "fillOpacity": 0.18,
    "strokeColor": "#22C55E",
    "strokeWidth": 1.0,
    "assetCount": 20
  },
  "H-09": {
    "code": "H-09",
    "name": "Blast Chiller 5",
    "risk": "high",
    "interactive": true,
    "left": 35.5692,
    "top": 78.4918,
    "width": 2.3348,
    "height": 7.1473,
    "svgPath": null,
    "fillColor": "#22C55E",
    "fillOpacity": 0.18,
    "strokeColor": "#22C55E",
    "strokeWidth": 1.0,
    "assetCount": 20
  },
  "H-10": {
    "code": "H-10",
    "name": "Holding Chiller 2",
    "risk": "high",
    "interactive": true,
    "left": 32.4362,
    "top": 69.9544,
    "width": 2.65,
    "height": 15.6847,
    "svgPath": null,
    "fillColor": "#22C55E",
    "fillOpacity": 0.18,
    "strokeColor": "#22C55E",
    "strokeWidth": 1.0,
    "assetCount": 35
  },
  "H-11": {
    "code": "H-11",
    "name": "Sanitation Room",
    "risk": "high",
    "interactive": true,
    "left": 36.4799,
    "top": 91.9054,
    "width": 1.1196,
    "height": 4.5114,
    "svgPath": null,
    "fillColor": "#22C55E",
    "fillOpacity": 0.18,
    "strokeColor": "#22C55E",
    "strokeWidth": 1.0,
    "assetCount": 6
  },
  "H-12": {
    "code": "H-12",
    "name": "Mixing Room",
    "risk": "high",
    "interactive": true,
    "left": 34.6247,
    "top": 91.6836,
    "width": 1.4583,
    "height": 4.7332,
    "svgPath": null,
    "fillColor": "#22C55E",
    "fillOpacity": 0.18,
    "strokeColor": "#22C55E",
    "strokeWidth": 1.0,
    "assetCount": 6
  },
  "H-13": {
    "code": "H-13",
    "name": "Vacuum Room",
    "risk": "high",
    "interactive": true,
    "left": 33.2413,
    "top": 91.4804,
    "width": 1.0399,
    "height": 4.9365,
    "svgPath": null,
    "fillColor": "#22C55E",
    "fillOpacity": 0.18,
    "strokeColor": "#22C55E",
    "strokeWidth": 1.0,
    "assetCount": 5
  },
  "H-14": {
    "code": "H-14",
    "name": "Air Blast Freezer",
    "risk": "high",
    "interactive": true,
    "left": 31.2083,
    "top": 91.4377,
    "width": 1.6675,
    "height": 4.9791,
    "svgPath": null,
    "fillColor": "#22C55E",
    "fillOpacity": 0.18,
    "strokeColor": "#22C55E",
    "strokeWidth": 1.0,
    "assetCount": 14
  },
  "H-15": {
    "code": "H-15",
    "name": "Equipment Room",
    "risk": "high",
    "interactive": true,
    "left": 25.9778,
    "top": 28.5448,
    "width": 1.7539,
    "height": 4.8267,
    "svgPath": null,
    "fillColor": "#22C55E",
    "fillOpacity": 0.18,
    "strokeColor": "#22C55E",
    "strokeWidth": 1.0,
    "assetCount": 12
  },
  "H-16": {
    "code": "H-16",
    "name": "Packaging Store Room",
    "risk": "high",
    "interactive": true,
    "left": 22.5027,
    "top": 28.5448,
    "width": 3.2676,
    "height": 4.8267,
    "svgPath": null,
    "fillColor": "#22C55E",
    "fillOpacity": 0.18,
    "strokeColor": "#22C55E",
    "strokeWidth": 1.0,
    "assetCount": 26
  },
  "H-17": {
    "code": "H-17",
    "name": "UV Entrance and Packaging Store",
    "risk": "high",
    "interactive": true,
    "left": 17.6652,
    "top": 28.6073,
    "width": 4.3316,
    "height": 4.8267,
    "svgPath": null,
    "fillColor": "#22C55E",
    "fillOpacity": 0.18,
    "strokeColor": "#22C55E",
    "strokeWidth": 1.0,
    "assetCount": 16
  },
  "H-18": {
    "code": "H-18",
    "name": "Packing Area",
    "risk": "high",
    "interactive": true,
    "left": 17.6652,
    "top": 28.3374,
    "width": 20.0431,
    "height": 71.6626,
    "svgPath": "M 17.6652 34.6164 C 17.6892 53.1804 17.7131 71.7445 17.7371 90.3085 L 22.2629 90.3085 C 22.2749 92.2195 22.2869 94.1305 22.2989 96.0415 L 27.8664 95.905 C 27.8784 97.27 27.8903 98.635 27.9023 100.0 L 30.5604 99.8635 L 30.6322 94.9495 L 30.8477 94.813 C 30.8597 93.357 30.8717 91.901 30.8836 90.445 L 37.6365 90.445 C 37.6485 89.1255 37.6604 87.806 37.6724 86.4865 L 32.2127 86.4865 C 32.2246 80.708 32.2366 74.9295 32.2486 69.151 L 37.6724 69.2875 C 37.6844 68.0134 37.6964 66.7395 37.7083 65.4654 L 32.2486 65.3289 C 32.2366 56.9569 32.2246 48.5849 32.2127 40.2129 L 30.4167 40.3494 C 30.4047 39.0754 30.3927 37.8014 30.3808 36.5274 L 28.7285 36.3909 L 28.7285 28.3374 L 28.046 28.3374 L 28.046 34.6164 L 17.6652 34.6164 Z",
    "fillColor": "#22C55E",
    "fillOpacity": 0.18,
    "strokeColor": "#00B050",
    "strokeWidth": 1.0,
    "assetCount": 77
  },
  "H-19": {
    "code": "H-19",
    "name": "Daily Cold Room",
    "risk": "high",
    "interactive": true,
    "left": 17.7861,
    "top": 92.2874,
    "width": 4.1384,
    "height": 3.0662,
    "svgPath": null,
    "fillColor": "#22C55E",
    "fillOpacity": 0.18,
    "strokeColor": "#22C55E",
    "strokeWidth": 1.0,
    "assetCount": 24
  },
  "L-01": {
    "code": "L-01",
    "name": "Incoming Warehouse 1",
    "risk": "low",
    "interactive": true,
    "left": 96.981,
    "top": 28.6073,
    "width": 1.9342,
    "height": 49.8845,
    "svgPath": null,
    "fillColor": "#EAB308",
    "fillOpacity": 0.18,
    "strokeColor": "#EAB308",
    "strokeWidth": 1.0,
    "assetCount": 28
  },
  "L-02": {
    "code": "L-02",
    "name": "Battery Charging",
    "risk": "low",
    "interactive": true,
    "left": 96.9682,
    "top": 80.3535,
    "width": 1.9342,
    "height": 5.4104,
    "svgPath": null,
    "fillColor": "#EAB308",
    "fillOpacity": 0.18,
    "strokeColor": "#EAB308",
    "strokeWidth": 1.0,
    "assetCount": 19
  },
  "L-03": {
    "code": "L-03",
    "name": "GRN Office",
    "risk": "low",
    "interactive": true,
    "left": 94.0623,
    "top": 28.8677,
    "width": 2.5578,
    "height": 6.6873,
    "svgPath": null,
    "fillColor": "#EAB308",
    "fillOpacity": 0.18,
    "strokeColor": "#EAB308",
    "strokeWidth": 1.0,
    "assetCount": 27
  },
  "L-04": {
    "code": "L-04",
    "name": "Frozen De-Box 1",
    "risk": "low",
    "interactive": true,
    "left": 94.0623,
    "top": 37.4122,
    "width": 2.5578,
    "height": 14.9096,
    "svgPath": null,
    "fillColor": "#EAB308",
    "fillOpacity": 0.18,
    "strokeColor": "#EAB308",
    "strokeWidth": 1.0,
    "assetCount": 36
  },
  "L-05": {
    "code": "L-05",
    "name": "Allergen De-Box 1",
    "risk": "low",
    "interactive": true,
    "left": 94.0623,
    "top": 54.1395,
    "width": 2.5578,
    "height": 10.0974,
    "svgPath": null,
    "fillColor": "#EAB308",
    "fillOpacity": 0.18,
    "strokeColor": "#EAB308",
    "strokeWidth": 1.0,
    "assetCount": 32
  },
  "L-06": {
    "code": "L-06",
    "name": "Non-Allergen-Chilled De-Box 1",
    "risk": "low",
    "interactive": true,
    "left": 94.0623,
    "top": 65.3153,
    "width": 2.5578,
    "height": 19.1736,
    "svgPath": null,
    "fillColor": "#EAB308",
    "fillOpacity": 0.18,
    "strokeColor": "#EAB308",
    "strokeWidth": 1.0,
    "assetCount": 45
  },
  "L-07": {
    "code": "L-07",
    "name": "Incoming Warehouse 2",
    "risk": "low",
    "interactive": true,
    "left": 84.6631,
    "top": 29.431,
    "width": 8.9719,
    "height": 18.8695,
    "svgPath": null,
    "fillColor": "#EAB308",
    "fillOpacity": 0.18,
    "strokeColor": "#EAB308",
    "strokeWidth": 1.0,
    "assetCount": 24
  },
  "L-08": {
    "code": "L-08",
    "name": "Allergen 1",
    "risk": "low",
    "interactive": true,
    "left": 90.8334,
    "top": 49.6165,
    "width": 2.8017,
    "height": 19.6032,
    "svgPath": null,
    "fillColor": "#EAB308",
    "fillOpacity": 0.18,
    "strokeColor": "#EAB308",
    "strokeWidth": 1.0,
    "assetCount": 16
  },
  "L-09": {
    "code": "L-09",
    "name": "AC Store",
    "risk": "low",
    "interactive": true,
    "left": 90.8334,
    "top": 70.364,
    "width": 2.8017,
    "height": 14.1248,
    "svgPath": null,
    "fillColor": "#EAB308",
    "fillOpacity": 0.18,
    "strokeColor": "#EAB308",
    "strokeWidth": 1.0,
    "assetCount": 18
  },
  "L-10": {
    "code": "L-10",
    "name": "Non-Allergen 1",
    "risk": "low",
    "interactive": true,
    "left": 84.6631,
    "top": 49.6165,
    "width": 5.6172,
    "height": 35.3826,
    "svgPath": null,
    "fillColor": "#EAB308",
    "fillOpacity": 0.18,
    "strokeColor": "#EAB308",
    "strokeWidth": 1.0,
    "assetCount": 31
  },
  "L-11": {
    "code": "L-11",
    "name": "Incoming Warehouse 3",
    "risk": "low",
    "interactive": true,
    "left": 68.3567,
    "top": 28.0303,
    "width": 15.7597,
    "height": 20.2703,
    "svgPath": "M 68.3567 28.0303 L 84.0894 28.235 L 84.1164 48.3005 L 80.8567 48.1982 L 80.8297 45.7412 L 68.4375 45.2293 L 68.3567 28.0303 Z",
    "fillColor": "#FFC000",
    "fillOpacity": 0.18,
    "strokeColor": "#EAB308",
    "strokeWidth": 1.0,
    "assetCount": 36
  },
  "L-12": {
    "code": "L-12",
    "name": "Chilled 1",
    "risk": "low",
    "interactive": true,
    "left": 81.2881,
    "top": 49.6215,
    "width": 2.6395,
    "height": 35.3826,
    "svgPath": null,
    "fillColor": "#EAB308",
    "fillOpacity": 0.18,
    "strokeColor": "#EAB308",
    "strokeWidth": 1.0,
    "assetCount": 15
  },
  "L-13": {
    "code": "L-13",
    "name": "Chilled 2",
    "risk": "low",
    "interactive": true,
    "left": 78.011,
    "top": 46.7953,
    "width": 2.6395,
    "height": 38.2825,
    "svgPath": null,
    "fillColor": "#EAB308",
    "fillOpacity": 0.18,
    "strokeColor": "#EAB308",
    "strokeWidth": 1.0,
    "assetCount": 21
  },
  "L-14": {
    "code": "L-14",
    "name": "Anti-Room 1",
    "risk": "low",
    "interactive": true,
    "left": 75.1499,
    "top": 46.9114,
    "width": 2.445,
    "height": 5.4104,
    "svgPath": null,
    "fillColor": "#EAB308",
    "fillOpacity": 0.18,
    "strokeColor": "#EAB308",
    "strokeWidth": 1.0,
    "assetCount": 8
  },
  "L-15": {
    "code": "L-15",
    "name": "Chicken Freezer 1",
    "risk": "low",
    "interactive": true,
    "left": 74.8357,
    "top": 53.9672,
    "width": 2.6395,
    "height": 31.037,
    "svgPath": null,
    "fillColor": "#EAB308",
    "fillOpacity": 0.18,
    "strokeColor": "#EAB308",
    "strokeWidth": 1.0,
    "assetCount": 15
  },
  "L-16": {
    "code": "L-16",
    "name": "Anti-Room 2",
    "risk": "low",
    "interactive": true,
    "left": 71.4924,
    "top": 46.9114,
    "width": 2.445,
    "height": 5.4104,
    "svgPath": null,
    "fillColor": "#EAB308",
    "fillOpacity": 0.18,
    "strokeColor": "#EAB308",
    "strokeWidth": 1.0,
    "assetCount": 8
  },
  "L-17": {
    "code": "L-17",
    "name": "Seafood Freezer",
    "risk": "low",
    "interactive": true,
    "left": 71.6604,
    "top": 54.3244,
    "width": 2.6395,
    "height": 13.6936,
    "svgPath": null,
    "fillColor": "#EAB308",
    "fillOpacity": 0.18,
    "strokeColor": "#EAB308",
    "strokeWidth": 1.0,
    "assetCount": 14
  },
  "L-18": {
    "code": "L-18",
    "name": "Chicken Freezer 2",
    "risk": "low",
    "interactive": true,
    "left": 71.769,
    "top": 69.6224,
    "width": 2.6395,
    "height": 15.7845,
    "svgPath": null,
    "fillColor": "#EAB308",
    "fillOpacity": 0.18,
    "strokeColor": "#EAB308",
    "strokeWidth": 1.0,
    "assetCount": 14
  },
  "L-19": {
    "code": "L-19",
    "name": "Cloak Room",
    "risk": "low",
    "interactive": true,
    "left": 74.2559,
    "top": 46.9114,
    "width": 0.6465,
    "height": 5.4104,
    "svgPath": null,
    "fillColor": "#EAB308",
    "fillOpacity": 0.18,
    "strokeColor": "#EAB308",
    "strokeWidth": 1.0,
    "assetCount": 3
  },
  "L-20": {
    "code": "L-20",
    "name": "Frozen De-Box 2",
    "risk": "low",
    "interactive": true,
    "left": 68.3836,
    "top": 46.253,
    "width": 2.8556,
    "height": 39.0049,
    "svgPath": "M 68.3836 46.253 L 71.2123 46.253 L 71.2392 85.258 L 69.4612 85.258 L 69.3535 64.3734 L 68.3836 64.3734 L 68.3836 46.253 Z",
    "fillColor": "#FFC000",
    "fillOpacity": 0.18,
    "strokeColor": "#EAB308",
    "strokeWidth": 1.0,
    "assetCount": 64
  },
  "L-21": {
    "code": "L-21",
    "name": "Staff Access",
    "risk": "low",
    "interactive": true,
    "left": 59.3678,
    "top": 37.4829,
    "width": 8.6925,
    "height": 58.2856,
    "svgPath": "M 61.2716 37.6194 L 68.0603 37.4829 L 68.0603 41.8509 L 62.3132 41.8509 C 62.3252 56.0469 62.3372 70.243 62.3491 84.439 L 60.8046 84.3025 C 60.8166 87.897 60.8285 91.4915 60.8405 95.086 L 60.8405 95.7685 L 59.4037 95.4955 C 59.3918 93.994 59.3798 92.4925 59.3678 90.991 L 60.0862 90.991 C 60.0742 86.896 60.0623 82.801 60.0503 78.706 L 61.2356 78.706 C 61.2476 65.0104 61.2596 51.3149 61.2716 37.6194 Z",
    "fillColor": "#FFC000",
    "fillOpacity": 0.18,
    "strokeColor": "#EAB308",
    "strokeWidth": 1.0,
    "assetCount": 112
  },
  "L-22": {
    "code": "L-22",
    "name": "Trolley Storage",
    "risk": "low",
    "interactive": true,
    "left": 63.7923,
    "top": 29.4311,
    "width": 4.1823,
    "height": 6.1239,
    "svgPath": null,
    "fillColor": "#EAB308",
    "fillOpacity": 0.18,
    "strokeColor": "#EAB308",
    "strokeWidth": 1.0,
    "assetCount": 19
  },
  "L-23": {
    "code": "L-23",
    "name": "Trolley Tray Wash Up",
    "risk": "low",
    "interactive": true,
    "left": 61.3474,
    "top": 29.4311,
    "width": 2.0794,
    "height": 6.1239,
    "svgPath": null,
    "fillColor": "#EAB308",
    "fillOpacity": 0.18,
    "strokeColor": "#EAB308",
    "strokeWidth": 1.0,
    "assetCount": 12
  },
  "L-24": {
    "code": "L-24",
    "name": "Rice Room",
    "risk": "low",
    "interactive": true,
    "left": 66.3479,
    "top": 43.3109,
    "width": 1.6266,
    "height": 6.9688,
    "svgPath": null,
    "fillColor": "#EAB308",
    "fillOpacity": 0.18,
    "strokeColor": "#EAB308",
    "strokeWidth": 1.0,
    "assetCount": 13
  },
  "L-25": {
    "code": "L-25",
    "name": "Wet Decanting",
    "risk": "low",
    "interactive": true,
    "left": 64.7478,
    "top": 43.3109,
    "width": 1.031,
    "height": 6.9688,
    "svgPath": null,
    "fillColor": "#EAB308",
    "fillOpacity": 0.18,
    "strokeColor": "#EAB308",
    "strokeWidth": 1.0,
    "assetCount": 6
  },
  "L-26": {
    "code": "L-26",
    "name": "Rice Washing",
    "risk": "low",
    "interactive": true,
    "left": 62.7526,
    "top": 43.3109,
    "width": 1.5632,
    "height": 6.9688,
    "svgPath": null,
    "fillColor": "#EAB308",
    "fillOpacity": 0.18,
    "strokeColor": "#EAB308",
    "strokeWidth": 1.0,
    "assetCount": 14
  },
  "L-27": {
    "code": "L-27",
    "name": "Allergen De-Box 2",
    "risk": "low",
    "interactive": true,
    "left": 62.7404,
    "top": 52.2444,
    "width": 5.1686,
    "height": 5.4104,
    "svgPath": null,
    "fillColor": "#EAB308",
    "fillOpacity": 0.18,
    "strokeColor": "#EAB308",
    "strokeWidth": 1.0,
    "assetCount": 40
  },
  "L-28": {
    "code": "L-28",
    "name": "Non-Allergen Chilled De-Box 2",
    "risk": "low",
    "interactive": true,
    "left": 62.724,
    "top": 59.0405,
    "width": 5.1686,
    "height": 5.4104,
    "svgPath": null,
    "fillColor": "#EAB308",
    "fillOpacity": 0.18,
    "strokeColor": "#EAB308",
    "strokeWidth": 1.0,
    "assetCount": 36
  },
  "L-29": {
    "code": "L-29",
    "name": "Chicken Defrost 1",
    "risk": "low",
    "interactive": true,
    "left": 62.7526,
    "top": 66.1139,
    "width": 6.3615,
    "height": 5.4104,
    "svgPath": null,
    "fillColor": "#EAB308",
    "fillOpacity": 0.18,
    "strokeColor": "#EAB308",
    "strokeWidth": 1.0,
    "assetCount": 39
  },
  "L-30": {
    "code": "L-30",
    "name": "Chicken Defrost 2",
    "risk": "low",
    "interactive": true,
    "left": 62.697,
    "top": 72.9922,
    "width": 6.3615,
    "height": 5.4104,
    "svgPath": null,
    "fillColor": "#EAB308",
    "fillOpacity": 0.18,
    "strokeColor": "#EAB308",
    "strokeWidth": 1.0,
    "assetCount": 37
  },
  "L-31": {
    "code": "L-31",
    "name": "Seafood Defrost",
    "risk": "low",
    "interactive": true,
    "left": 62.694,
    "top": 79.6673,
    "width": 6.3615,
    "height": 5.4104,
    "svgPath": null,
    "fillColor": "#EAB308",
    "fillOpacity": 0.18,
    "strokeColor": "#EAB308",
    "strokeWidth": 1.0,
    "assetCount": 42
  },
  "L-32": {
    "code": "L-32",
    "name": "Staff Access LR Area-1",
    "risk": "low",
    "interactive": true,
    "left": 51.3578,
    "top": 33.9339,
    "width": 9.6264,
    "height": 7.917,
    "svgPath": "M 51.3578 37.3464 L 51.3578 41.8509 L 60.9842 41.5779 L 60.9842 34.2069 L 59.727 33.9339 L 59.727 37.3464 L 51.3578 37.3464 Z",
    "fillColor": "#FFC000",
    "fillOpacity": 0.18,
    "strokeColor": "#E5AF08",
    "strokeWidth": 1.0,
    "assetCount": 46
  },
  "L-33": {
    "code": "L-33",
    "name": "Waste Out",
    "risk": "low",
    "interactive": true,
    "left": 59.727,
    "top": 28.4739,
    "width": 1.1903,
    "height": 4.485,
    "svgPath": null,
    "fillColor": "#EAB308",
    "fillOpacity": 0.18,
    "strokeColor": "#EAB308",
    "strokeWidth": 1.0,
    "assetCount": 13
  },
  "L-34": {
    "code": "L-34",
    "name": "Storage Non-Allergen",
    "risk": "low",
    "interactive": true,
    "left": 57.6636,
    "top": 28.9379,
    "width": 1.6333,
    "height": 6.617,
    "svgPath": null,
    "fillColor": "#FFC000",
    "fillOpacity": 0.18,
    "strokeColor": "#EAB308",
    "strokeWidth": 1.0,
    "assetCount": 22
  },
  "L-35": {
    "code": "L-35",
    "name": "Washing Non-Allergen",
    "risk": "low",
    "interactive": true,
    "left": 56.1739,
    "top": 28.8235,
    "width": 1.0747,
    "height": 6.617,
    "svgPath": null,
    "fillColor": "#EAB308",
    "fillOpacity": 0.18,
    "strokeColor": "#EAB308",
    "strokeWidth": 1.0,
    "assetCount": 14
  },
  "L-36": {
    "code": "L-36",
    "name": "Storage Allergen",
    "risk": "low",
    "interactive": true,
    "left": 54.3545,
    "top": 28.8235,
    "width": 1.4045,
    "height": 6.617,
    "svgPath": null,
    "fillColor": "#EAB308",
    "fillOpacity": 0.18,
    "strokeColor": "#EAB308",
    "strokeWidth": 1.0,
    "assetCount": 22
  },
  "L-37": {
    "code": "L-37",
    "name": "Washing Allergen",
    "risk": "low",
    "interactive": true,
    "left": 52.8648,
    "top": 28.7222,
    "width": 1.0747,
    "height": 6.617,
    "svgPath": null,
    "fillColor": "#EAB308",
    "fillOpacity": 0.18,
    "strokeColor": "#EAB308",
    "strokeWidth": 1.0,
    "assetCount": 12
  },
  "L-38": {
    "code": "L-38",
    "name": "Equip and Trolley Wash up",
    "risk": "low",
    "interactive": true,
    "left": 49.5893,
    "top": 28.8865,
    "width": 2.8605,
    "height": 6.617,
    "svgPath": null,
    "fillColor": "#EAB308",
    "fillOpacity": 0.18,
    "strokeColor": "#EAB308",
    "strokeWidth": 1.0,
    "assetCount": 21
  },
  "L-39": {
    "code": "L-39",
    "name": "Allergen Weigh",
    "risk": "low",
    "interactive": true,
    "left": 56.087,
    "top": 42.4547,
    "width": 4.8988,
    "height": 6.124,
    "svgPath": null,
    "fillColor": "#FFC000",
    "fillOpacity": 0.18,
    "strokeColor": "#EAB308",
    "strokeWidth": 1.0,
    "assetCount": 18
  },
  "L-40": {
    "code": "L-40",
    "name": "Allergen Chilled Weigh",
    "risk": "low",
    "interactive": true,
    "left": 54.7124,
    "top": 42.573,
    "width": 6.1451,
    "height": 11.7514,
    "svgPath": "M 54.8111 42.573 L 55.7646 42.6413 C 55.7526 45.0662 55.7407 47.4912 55.7287 49.9161 L 60.8574 49.8137 C 60.8604 51.1808 60.7915 52.9574 60.7945 54.3244 L 54.7124 54.2561 C 54.7393 45.6639 54.7842 51.1653 54.8111 42.573 Z",
    "fillColor": "#EAB308",
    "fillOpacity": 0.18,
    "strokeColor": "#EAB308",
    "strokeWidth": 1.0,
    "assetCount": 47
  },
  "L-41": {
    "code": "L-41",
    "name": "Non-Allergen 2",
    "risk": "low",
    "interactive": true,
    "left": 51.3411,
    "top": 43.121,
    "width": 3.1598,
    "height": 10.7579,
    "svgPath": null,
    "fillColor": "#EAB308",
    "fillOpacity": 0.18,
    "strokeColor": "#EAB308",
    "strokeWidth": 1.0,
    "assetCount": 17
  },
  "L-42": {
    "code": "L-42",
    "name": "Staging Area Chilled",
    "risk": "low",
    "interactive": true,
    "left": 49.2811,
    "top": 43.5506,
    "width": 1.7488,
    "height": 10.4166,
    "svgPath": null,
    "fillColor": "#EAB308",
    "fillOpacity": 0.18,
    "strokeColor": "#EAB308",
    "strokeWidth": 1.0,
    "assetCount": 27
  },
  "L-43": {
    "code": "L-43",
    "name": "Veg Preparation",
    "risk": "low",
    "interactive": true,
    "left": 51.5733,
    "top": 55.4785,
    "width": 9.4125,
    "height": 9.129,
    "svgPath": null,
    "fillColor": "#EAB308",
    "fillOpacity": 0.18,
    "strokeColor": "#EAB308",
    "strokeWidth": 1.0,
    "assetCount": 34
  },
  "L-44": {
    "code": "L-44",
    "name": "Veg Chill",
    "risk": "low",
    "interactive": true,
    "left": 49.3216,
    "top": 55.9227,
    "width": 1.9207,
    "height": 8.9725,
    "svgPath": null,
    "fillColor": "#EAB308",
    "fillOpacity": 0.18,
    "strokeColor": "#EAB308",
    "strokeWidth": 1.0,
    "assetCount": 28
  },
  "L-45": {
    "code": "L-45",
    "name": "Chicken Preparation",
    "risk": "low",
    "interactive": true,
    "left": 51.5733,
    "top": 66.5649,
    "width": 9.4125,
    "height": 10.9497,
    "svgPath": null,
    "fillColor": "#EAB308",
    "fillOpacity": 0.18,
    "strokeColor": "#EAB308",
    "strokeWidth": 1.0,
    "assetCount": 74
  },
  "L-46": {
    "code": "L-46",
    "name": "Chicken Chill",
    "risk": "low",
    "interactive": true,
    "left": 49.2811,
    "top": 66.6649,
    "width": 1.9855,
    "height": 16.8314,
    "svgPath": null,
    "fillColor": "#EAB308",
    "fillOpacity": 0.18,
    "strokeColor": "#EAB308",
    "strokeWidth": 1.0,
    "assetCount": 40
  },
  "L-47": {
    "code": "L-47",
    "name": "Seafood Preparation",
    "risk": "low",
    "interactive": true,
    "left": 54.1217,
    "top": 79.2094,
    "width": 5.6053,
    "height": 10.4166,
    "svgPath": null,
    "fillColor": "#EAB308",
    "fillOpacity": 0.18,
    "strokeColor": "#EAB308",
    "strokeWidth": 1.0,
    "assetCount": 38
  },
  "L-48": {
    "code": "L-48",
    "name": "Seafood Chill",
    "risk": "low",
    "interactive": true,
    "left": 51.6092,
    "top": 79.3459,
    "width": 2.0394,
    "height": 10.4166,
    "svgPath": null,
    "fillColor": "#EAB308",
    "fillOpacity": 0.18,
    "strokeColor": "#EAB308",
    "strokeWidth": 1.0,
    "assetCount": 29
  },
  "L-49": {
    "code": "L-49",
    "name": "LR War RM",
    "risk": "low",
    "interactive": true,
    "left": 49.3873,
    "top": 85.258,
    "width": 1.855,
    "height": 4.6218,
    "svgPath": null,
    "fillColor": "#EAB308",
    "fillOpacity": 0.18,
    "strokeColor": "#EAB308",
    "strokeWidth": 1.0,
    "assetCount": 4
  },
  "L-50": {
    "code": "L-50",
    "name": "Staff Access LR Area-2",
    "risk": "low",
    "interactive": true,
    "left": 48.8578,
    "top": 91.1895,
    "width": 10.2802,
    "height": 3.6049,
    "svgPath": null,
    "fillColor": "#EAB308",
    "fillOpacity": 0.18,
    "strokeColor": "#EAB308",
    "strokeWidth": 1.0,
    "assetCount": 19
  },
  "L-51": {
    "code": "L-51",
    "name": "LR Area",
    "risk": "low",
    "interactive": true,
    "left": 40.8693,
    "top": 28.4739,
    "width": 10.2011,
    "height": 66.8851,
    "svgPath": "M 40.8693 28.6104 L 49.2744 28.4739 L 49.2744 37.3464 L 51.0345 37.4829 C 51.0465 38.8479 51.0584 40.2129 51.0704 41.5779 L 48.6638 41.7144 L 48.7716 89.7625 L 48.556 90.0355 L 48.556 95.086 L 40.8693 95.359 C 40.8932 73.155 40.9172 50.9509 40.8693 28.6104 Z",
    "fillColor": "#FFC000",
    "fillOpacity": 0.18,
    "strokeColor": "#E9B208",
    "strokeWidth": 1.0,
    "assetCount": 64
  },
  "L-52": {
    "code": "L-52",
    "name": "Wet Waste",
    "risk": "low",
    "interactive": true,
    "left": 56.8534,
    "top": 20.5053,
    "width": 3.6998,
    "height": 6.1239,
    "svgPath": null,
    "fillColor": "#EAB308",
    "fillOpacity": 0.18,
    "strokeColor": "#EAB308",
    "strokeWidth": 1.0,
    "assetCount": 12
  },
  "L-53": {
    "code": "L-53",
    "name": "Cardboard and Waste Compactors",
    "risk": "low",
    "interactive": true,
    "left": 60.9858,
    "top": 20.5669,
    "width": 3.6998,
    "height": 6.1239,
    "svgPath": null,
    "fillColor": "#EAB308",
    "fillOpacity": 0.18,
    "strokeColor": "#EAB308",
    "strokeWidth": 1.0,
    "assetCount": 18
  },
  "L-54": {
    "code": "L-54",
    "name": "Washing Area EE-Point Water Drain",
    "risk": "low",
    "interactive": true,
    "left": 65.0135,
    "top": 20.5669,
    "width": 3.0681,
    "height": 6.1239,
    "svgPath": null,
    "fillColor": "#EAB308",
    "fillOpacity": 0.18,
    "strokeColor": "#EAB308",
    "strokeWidth": 1.0,
    "assetCount": 10
  },
  "M-01": {
    "code": "M-01",
    "name": "Dispatch Office",
    "risk": "medium",
    "interactive": true,
    "left": 16.7048,
    "top": 15.4052,
    "width": 4.2688,
    "height": 8.0041,
    "svgPath": "M 17.7861 27.5184 L 17.7861 11.2961 L 19.8923 11.2961 L 19.8923 27.5184 Z",
    "fillColor": "#0EA5E9",
    "fillOpacity": 0.18,
    "strokeColor": "#0EA5E9",
    "strokeWidth": 1.0,
    "assetCount": 22
  },
  "M-02": {
    "code": "M-02",
    "name": "Outgoing Warehouse",
    "risk": "medium",
    "interactive": true,
    "left": 0.9909,
    "top": 3.2681,
    "width": 16.4229,
    "height": 11.0275,
    "svgPath": null,
    "fillColor": "#0EA5E9",
    "fillOpacity": 0.18,
    "strokeColor": "#0EA5E9",
    "strokeWidth": 1.0,
    "assetCount": 108
  },
  "M-03": {
    "code": "M-03",
    "name": "Ambient Packaging Store RM",
    "risk": "medium",
    "interactive": true,
    "left": 8.1735,
    "top": 15.131,
    "width": 9.1325,
    "height": 19.656,
    "svgPath": "M 8.1735 15.131 L 17.2791 15.2334 L 17.306 30.3849 L 14.9623 30.1801 L 14.9892 34.6846 L 9.9515 34.787 L 9.9246 30.2825 L 8.1735 30.2825 L 8.1735 15.131 Z",
    "fillColor": "#00B0F0",
    "fillOpacity": 0.18,
    "strokeColor": "#00B0F0",
    "strokeWidth": 1.0,
    "assetCount": 22
  },
  "M-04": {
    "code": "M-04",
    "name": "Cloak Room",
    "risk": "medium",
    "interactive": true,
    "left": 8.163,
    "top": 31.5177,
    "width": 1.4791,
    "height": 3.2693,
    "svgPath": null,
    "fillColor": "#0EA5E9",
    "fillOpacity": 0.18,
    "strokeColor": "#0EA5E9",
    "strokeWidth": 1.0,
    "assetCount": 5
  },
  "M-05": {
    "code": "M-05",
    "name": "Manual Palletizing",
    "risk": "medium",
    "interactive": true,
    "left": 0.8908,
    "top": 15.2029,
    "width": 16.523,
    "height": 79.6783,
    "svgPath": "M 5.3808 15.2333 C 5.3927 40.5314 5.4047 65.8294 5.4167 91.1274 L 0.8908 91.1274 C 0.9028 92.3104 0.9148 93.4935 0.9267 94.6764 L 14.7288 94.8812 C 14.7168 93.3797 14.7318 91.9806 14.7198 90.4791 L 17.4138 90.4449 L 17.4138 31.4768 L 15.2586 31.3403 C 15.2467 32.8418 15.3155 34.3433 15.3035 35.8448 L 7.931 35.7083 L 7.931 15.3357 C 7.081 15.4722 6.2309 15.0968 5.3808 15.2333 Z",
    "fillColor": "#00B0F0",
    "fillOpacity": 0.18,
    "strokeColor": "#00B0F0",
    "strokeWidth": 1.0,
    "assetCount": 58
  },
  "M-06": {
    "code": "M-06",
    "name": "HR Utensil Wash Up and Storage",
    "risk": "medium",
    "interactive": true,
    "left": 15.0023,
    "top": 91.4804,
    "width": 2.4115,
    "height": 3.9159,
    "svgPath": null,
    "fillColor": "#0EA5E9",
    "fillOpacity": 0.18,
    "strokeColor": "#0EA5E9",
    "strokeWidth": 1.0,
    "assetCount": 14
  },
  "M-07": {
    "code": "M-07",
    "name": "Anti Room 3",
    "risk": "medium",
    "interactive": true,
    "left": 0.9909,
    "top": 15.52,
    "width": 4.1384,
    "height": 5.9974,
    "svgPath": null,
    "fillColor": "#0EA5E9",
    "fillOpacity": 0.18,
    "strokeColor": "#0EA5E9",
    "strokeWidth": 1.0,
    "assetCount": 30
  },
  "M-08": {
    "code": "M-08",
    "name": "Frozen Room 1",
    "risk": "medium",
    "interactive": true,
    "left": 0.9909,
    "top": 22.6044,
    "width": 4.1384,
    "height": 26.5047,
    "svgPath": null,
    "fillColor": "#0EA5E9",
    "fillOpacity": 0.18,
    "strokeColor": "#0EA5E9",
    "strokeWidth": 1.0,
    "assetCount": 11
  },
  "M-09": {
    "code": "M-09",
    "name": "Anti Room 4",
    "risk": "medium",
    "interactive": true,
    "left": 0.9909,
    "top": 50.4961,
    "width": 4.1384,
    "height": 7.7386,
    "svgPath": null,
    "fillColor": "#0EA5E9",
    "fillOpacity": 0.18,
    "strokeColor": "#0EA5E9",
    "strokeWidth": 1.0,
    "assetCount": 30
  },
  "M-10": {
    "code": "M-10",
    "name": "Frozen Room 2",
    "risk": "medium",
    "interactive": true,
    "left": 0.9909,
    "top": 59.8642,
    "width": 4.1384,
    "height": 30.374,
    "svgPath": null,
    "fillColor": "#0EA5E9",
    "fillOpacity": 0.18,
    "strokeColor": "#0EA5E9",
    "strokeWidth": 1.0,
    "assetCount": 9
  }
}
